iprange/__init__.py
iprange/iprange.py
iprange_python-0.0.9.dist-info/LICENSE
iprange_python-0.0.9.dist-info/METADATA
iprange_python-0.0.9.dist-info/WHEEL
iprange_python-0.0.9.dist-info/top_level.txt
iprange_python-0.0.9.dist-info/RECORD
