Metadata-Version: 2.1
Name: iprange-python
Version: 0.0.9
Summary: Redis as a storage for IP range
Home-page: https://github.com/lucasrodcosta/iprange-python
Author: Lucas Costa
Author-email: lucasrodcosta@gmail.com
License: MIT
License-File: LICENSE
Requires-Dist: netaddr (>=0.7.19)
Requires-Dist: redis (>=2.10.6)
Requires-Dist: redis-py-cluster (>=1.3.4)
